auto_surprise/__init__.py
auto_surprise/__version__.py
auto_surprise/constants.py
auto_surprise/engine.py
auto_surprise/exceptions.py
auto_surprise/trainer.py
auto_surprise/validation_util.py
auto_surprise/algorithms/__init__.py
auto_surprise/algorithms/base.py
auto_surprise/algorithms/spaces.py
auto_surprise/context/__init__.py
auto_surprise/context/backend.py
auto_surprise/context/limits.py
auto_surprise/context/result_logging_manager.py
auto_surprise/strategies/__init__.py
auto_surprise/strategies/base.py
auto_surprise/strategies/basic_reduction.py
auto_surprise/strategies/smbo.py
tests/__init__.py
tests/test_engine.py
tests/test_trainer.py
tests/test_validation_util.py
tests/utils.py
tests/algorithms/__init__.py
tests/algorithms/test_base.py
auto_surprise-0.1.9.dist-info/LICENSE
auto_surprise-0.1.9.dist-info/METADATA
auto_surprise-0.1.9.dist-info/WHEEL
auto_surprise-0.1.9.dist-info/top_level.txt
auto_surprise-0.1.9.dist-info/RECORD
