Metadata-Version: 2.1
Name: auto-surprise
Version: 0.1.9
Summary: A python package that automates algorithm selection and hyperparameter tuning for the recommender system library Surprise
Home-page: https://github.com/ISG-Siegen/Auto-Surprise
Author: Rohan Anand
Author-email: anandr@tcd.ie
Classifier: Programming Language :: Python :: 3
Classifier: License :: OSI Approved :: MIT License
Classifier: Operating System :: OS Independent
Requires-Python: >=3.8
License-File: LICENSE
Requires-Dist: cloudpickle (==2.2.1)
Requires-Dist: future (==0.18.3)
Requires-Dist: hyperopt (==0.2.7)
Requires-Dist: joblib (==1.2.0)
Requires-Dist: markdown-it-py (==2.2.0)
Requires-Dist: mdurl (==0.1.2)
Requires-Dist: networkx (==3.1)
Requires-Dist: numpy (==1.24.2)
Requires-Dist: pandas (==2.0.0)
Requires-Dist: py4j (==0.10.9.7)
Requires-Dist: Pygments (==2.14.0)
Requires-Dist: python-dateutil (==2.8.2)
Requires-Dist: pytz (==2023.3)
Requires-Dist: rich (==13.3.3)
Requires-Dist: scikit-learn (==1.2.2)
Requires-Dist: scikit-surprise (==1.1.3)
Requires-Dist: scipy (==1.10.1)
Requires-Dist: six (==1.16.0)
Requires-Dist: threadpoolctl (==3.1.0)
Requires-Dist: tqdm (==4.65.0)
Requires-Dist: typing-extensions (==4.5.0)
Requires-Dist: tzdata (==2023.3)
